Excersise_2_Group_3/SRC/shift_register.v
`timescale 1ns / 1ps
module shift_reg  #(parameter n=8) (input si,                    // Serial Input
                                    input clk,                   // Clock
                                    input en,                    // Enable
                                    input [n-1:0] din,           // Parallel Input
                                    input rstn,                  // ~Reset
                                    input pl,                    // Parallel Input Enable
                                    output reg so,              // Serial Output
                                    output reg [n-1:0] tempParallelOutput); // Content of Register
    

   always @ (posedge clk, negedge rstn)
    if (!rstn) begin
        tempParallelOutput <= 0;
        so <= 0;
    end
    else begin
        if (!pl) begin                                                  //If Parallel Load is 0 Serial Mode is enabled
            if (en) begin
                so <= tempParallelOutput[0];                            //LSB of Shift Register content goes to Serial Output
                tempParallelOutput <= {si, tempParallelOutput[n-1:1]};  //Shift Register Content is shifted right and Serial Input Becomes the new MSB
            end
            else begin
                tempParallelOutput <= tempParallelOutput;               //If enable is 0 Content of Shift Register remains the same 
            end
        end
        else begin          
            tempParallelOutput <= din;                                  //In Parallel Mode new content of Shift Register is din
        end    
    end
endmodule

Excersise_2_Group_3/SRC/shift_register_tb.v
module tb_shift_reg;
   parameter len = 16;        // New Length of Shift Register
 
        reg si;                    // Serial Input
        reg clk;                   // Clock
        reg en;                    // Enable
        reg [len-1:0] din;           // Parallel Input
        reg rstn;                  // ~Reset
        reg pl;                    // Parallel Input Enable
        wire so;                   // Serial Output
        wire [len-1:0] tempParallelOutput;
   // Instantiate design (16-bit shift register) by passing len and connect with TestBench signals
   shift_reg  #(len) shift_reg0  (  .si (si),
                                    .clk (clk),
                                    .en (en),
                                    .din (din),
                                    .rstn (rstn),
                                    .pl (pl),
                                    .so (so),
                                    .tempParallelOutput (tempParallelOutput));
 
   //clock time period = 10ns (`timescale 1ns / 1ps)
   always #5 clk = ~clk;
 
   // Initialize variables to default values at time 0
   initial begin
      clk <= 0;
      en <= 1'b0;
      din <= 0;
      si <= 1'b0;
      pl <= 1'b0;
   end
 
   initial begin
 
      rstn <= 1'b0;     //Reset Circuit for 20ns
      #20 rstn <= 1;
          en <= 1;
 
    // For 7 clocks, drive alternate values to data pin
      repeat (10) @ (posedge clk)
         si <= ~si;
 
 
      //Drive nothing for next 7 clocks, allow shift register to simply shift
        repeat (10) @ (posedge clk);
      
    //Parallel Load Mode Test
        pl <= 1'b1;
        din <= 16'hff00; //Parallel Load Value 1111111100000000 in binary
        #20 pl <= 1'b0;
    //Drive nothing for next 7 clocks, allow shift register to simply shift
        
        repeat (10) @ (posedge clk);
      //Finish the simulation
      $finish;
   end
 
   // Monitor values of these variables and print them into the logfile for debug
   initial begin
      $monitor ("rstn=%0b din=%b, en=%0b, pl=%b, out=%b, in=%b, Register Content=%b", rstn, din, en, pl, so, si, tempParallelOutput);
  	  $dumpvars;
      $dumpfile("dump.vcd");
   end
endmodule

Excersise_2_Group_3/CODE_PRODUCED_FILES/dump.vcd
$date
	Sun Apr 09 17:31:43 2023
$end
$version
	ModelSim Version 5.7f
$end
$timescale
	1ps
$end
$scope module tb_shift_reg $end
$var parameter 32 ! len $end
$var reg 1 " si $end
$var reg 1 # clk $end
$var reg 1 $ en $end
$var reg 16 % din [15:0] $end
$var reg 1 & rstn $end
$var reg 1 ' pl $end
$var wire 1 ( so $end
$var wire 1 ) tempParallelOutput [15] $end
$var wire 1 * tempParallelOutput [14] $end
$var wire 1 + tempParallelOutput [13] $end
$var wire 1 , tempParallelOutput [12] $end
$var wire 1 - tempParallelOutput [11] $end
$var wire 1 . tempParallelOutput [10] $end
$var wire 1 / tempParallelOutput [9] $end
$var wire 1 0 tempParallelOutput [8] $end
$var wire 1 1 tempParallelOutput [7] $end
$var wire 1 2 tempParallelOutput [6] $end
$var wire 1 3 tempParallelOutput [5] $end
$var wire 1 4 tempParallelOutput [4] $end
$var wire 1 5 tempParallelOutput [3] $end
$var wire 1 6 tempParallelOutput [2] $end
$var wire 1 7 tempParallelOutput [1] $end
$var wire 1 8 tempParallelOutput [0] $end
$scope module shift_reg0 $end
$var parameter 32 9 n $end
$var wire 1 : si $end
$var wire 1 ; clk $end
$var wire 1 < en $end
$var wire 1 = din [15] $end
$var wire 1 > din [14] $end
$var wire 1 ? din [13] $end
$var wire 1 @ din [12] $end
$var wire 1 A din [11] $end
$var wire 1 B din [10] $end
$var wire 1 C din [9] $end
$var wire 1 D din [8] $end
$var wire 1 E din [7] $end
$var wire 1 F din [6] $end
$var wire 1 G din [5] $end
$var wire 1 H din [4] $end
$var wire 1 I din [3] $end
$var wire 1 J din [2] $end
$var wire 1 K din [1] $end
$var wire 1 L din [0] $end
$var wire 1 M rstn $end
$var wire 1 N pl $end
$var reg 1 O so $end
$var reg 16 P tempParallelOutput [15:0] $end
$upscope $end
$upscope $end
$enddefinitions $end
#0
$dumpvars
b10000 !
b10000 9
0"
0#
0$
b0 %
0&
0'
0O
b0 P
0(
08
07
06
05
04
03
02
01
00
0/
0.
0-
0,
0+
0*
0)
0N
0M
0L
0K
0J
0I
0H
0G
0F
0E
0D
0C
0B
0A
0@
0?
0>
0=
0<
0;
0:
$end
#5
1#
1;
#10
0#
0;
#15
1#
1;
#20
0#
0;
1&
1$
1M
1<
#25
1#
1;
1"
1:
#30
0#
0;
#35
1#
1;
0"
b1000000000000000 P
1)
0:
#40
0#
0;
#45
1#
1;
1"
b100000000000000 P
1*
0)
1:
#50
0#
0;
#55
1#
1;
0"
b1010000000000000 P
1+
0*
1)
0:
#60
0#
0;
#65
1#
1;
1"
b101000000000000 P
1,
0+
1*
0)
1:
#70
0#
0;
#75
1#
1;
0"
b1010100000000000 P
1-
0,
1+
0*
1)
0:
#80
0#
0;
#85
1#
1;
1"
b101010000000000 P
1.
0-
1,
0+
1*
0)
1:
#90
0#
0;
#95
1#
1;
0"
b1010101000000000 P
1/
0.
1-
0,
1+
0*
1)
0:
#100
0#
0;
#105
1#
1;
1"
b101010100000000 P
10
0/
1.
0-
1,
0+
1*
0)
1:
#110
0#
0;
#115
1#
1;
0"
b1010101010000000 P
11
00
1/
0.
1-
0,
1+
0*
1)
0:
#120
0#
0;
#125
1#
1;
b101010101000000 P
12
01
10
0/
1.
0-
1,
0+
1*
0)
#130
0#
0;
#135
1#
1;
b10101010100000 P
13
02
11
00
1/
0.
1-
0,
1+
0*
#140
0#
0;
#145
1#
1;
b1010101010000 P
14
03
12
01
10
0/
1.
0-
1,
0+
#150
0#
0;
#155
1#
1;
b101010101000 P
15
04
13
02
11
00
1/
0.
1-
0,
#160
0#
0;
#165
1#
1;
b10101010100 P
16
05
14
03
12
01
10
0/
1.
0-
#170
0#
0;
#175
1#
1;
b1010101010 P
17
06
15
04
13
02
11
00
1/
0.
#180
0#
0;
#185
1#
1;
b101010101 P
18
07
16
05
14
03
12
01
10
0/
#190
0#
0;
#195
1#
1;
1O
b10101010 P
08
17
06
15
04
13
02
11
00
1(
#200
0#
0;
#205
1#
1;
0O
b1010101 P
18
07
16
05
14
03
12
01
0(
#210
0#
0;
#215
1#
1;
1'
b1111111100000000 %
1O
b101010 P
08
17
06
15
04
13
02
1D
1C
1B
1A
1@
1?
1>
1=
1N
1(
#220
0#
0;
#225
1#
1;
b1111111100000000 P
07
05
03
10
1/
1.
1-
1,
1+
1*
1)
#230
0#
0;
#235
1#
1;
0'
0N
#240
0#
0;
#245
1#
1;
0O
b111111110000000 P
11
0)
0(
#250
0#
0;
#255
1#
1;
b11111111000000 P
12
0*
#260
0#
0;
#265
1#
1;
b1111111100000 P
13
0+
#270
0#
0;
#275
1#
1;
b111111110000 P
14
0,
#280
0#
0;
#285
1#
1;
b11111111000 P
15
0-
#290
0#
0;
#295
1#
1;
b1111111100 P
16
0.
#300
0#
0;
#305
1#
1;
b111111110 P
17
0/
#310
0#
0;
#315
1#
1;
b11111111 P
18
00
